{"cameraMode":{"drawMode":0,"name":"Shaded","section":"Shading Mode"},"sceneLighting":true,"audioPlay":false,"sceneViewState":{"m_AlwaysRefresh":false,"showFog":true,"showSkybox":true,"showFlares":true,"showImageEffects":true,"showParticleSystems":true,"showVisualEffectGraphs":true,"m_FxEnabled":true},"in2DMode":false,"pivot":{"x":-3.258143424987793,"y":-0.8888654112815857,"z":0.3111565113067627},"rotation":{"x":0.0311528779566288,"y":-0.948360800743103,"z":0.09850721806287766,"w":0.29991769790649416},"size":7.180537223815918,"orthographic":false}